Workbook
Name aporte: APP!$D$11:$D$11
Name qtd_anos: APP!$D$12:$D$12
Name rendimento_carteira: APP!$D$26:$D$26
Name salario: APP!$D$25:$D$25
Name taxa_mensal: APP!$D$13:$D$13

Sheet APP
B10: INVESTIMENTO MENSAL
B11: Quanto investir por mês? | D11: 500
B12: Por quantos anos? | D12: 5
B13: Taxa de rendimento mensal? | D13: 0.01079
B14: Patrimônio acumulado? | D14: {=FV(taxa_mensal,qtd_anos*12,aporte*-1)} -> 41888.457
B15: Dividendos mensais? | D15: =D14*1% -> 418.88457
B17: CENÁRIOS | D17: DIVIDENDOS
A18: 2 | B18: Quanto em 2 anos? | C18: =FV($D$13,$A18*12,$D$11*-1) -> 13613.814 | D18: =$C18*1% -> 136.13814
A19: 5 | B19: Quanto em 5 anos? | C19: =FV($D$13,$A19*12,$D$11*-1) -> 41888.457 | D19: =$C19*1% -> 418.88457
A20: 10 | B20: Quanto em 10 anos? | C20: =FV($D$13,$A20*12,$D$11*-1) -> 121642.11 | D20: =$C20*1% -> 1216.4211
A21: 20 | B21: Quanto em 20 anos? | C21: =FV($D$13,$A21*12,$D$11*-1) -> 562599.2 | D21: =$C21*1% -> 5625.992
A22: 30 | B22: Quanto em 30 anos? | C22: =FV($D$13,$A22*12,$D$11*-1) -> 2161084.8 | D22: =$C22*1% -> 21610.848
B24: CONFIGURAÇÕES
B25: Salário | D25: 5000
B26: Rendimento Carteira | D26: 0.01
B27: Sugestão de Investimento | D27: {=salario*30%} -> 1500
B29: PERFIL | D29: Conservador
B30: VALOR A SER INVESTIDO POR MÊS | D30: 200
B32: TIPO DE FII | C32: PERCENTUAL SUGERIDO | D32: VALORES
B33: Papel | C33: =VLOOKUP($D$29&"-"&$B33,Report!$A$1:$D$18,4,FALSE) -> 0.5 | D33: =C33*$D$30 -> 100
B34: Tijolo | C34: =VLOOKUP($D$29&"-"&$B34,Report!$A$1:$D$18,4,FALSE) -> 0.1 | D34: =C34*$D$30 -> 20
B35: Híbridos | C35: =VLOOKUP($D$29&"-"&$B35,Report!$A$1:$D$18,4,FALSE) -> 0.1 | D35: =C35*$D$30 -> 20
B36: FOFs | C36: =VLOOKUP($D$29&"-"&$B36,Report!$A$1:$D$18,4,FALSE) -> 0 | D36: =C36*$D$30 -> 0
B37: Desenvolvimento | C37: =VLOOKUP($D$29&"-"&$B37,Report!$A$1:$D$18,4,FALSE) -> 0 | D37: =C37*$D$30 -> 0
B38: Hotelarias | C38: =VLOOKUP($D$29&"-"&$B38,Report!$A$1:$D$18,4,FALSE) -> 0.3 | D38: =C38*$D$30 -> 60
B39: TOTAL | D39: =SUM(D33:D38) -> 200

Sheet Report
A1: =$B1&"-"&$C1 -> Agressivo-Papel | B1: Agressivo | C1: Papel | D1: 0.5
A2: =$B2&"-"&$C2 -> Agressivo-Tijolo | B2: Agressivo | C2: Tijolo | D2: 0.1
A3: =$B3&"-"&$C3 -> Agressivo-Híbridos | B3: Agressivo | C3: Híbridos | D3: 0.05
A4: =$B4&"-"&$C4 -> Agressivo-FOFs | B4: Agressivo | C4: FOFs | D4: 0.05
A5: =$B5&"-"&$C5 -> Agressivo-Desenvolvimento | B5: Agressivo | C5: Desenvolvimento | D5: 0.2
A6: =$B6&"-"&$C6 -> Agressivo-Hotelarias | B6: Agressivo | C6: Hotelarias | D6: 0.1
A7: =$B7&"-"&$C7 -> Conservador-Papel | B7: Conservador | C7: Papel | D7: 0.5
A8: =$B8&"-"&$C8 -> Conservador-Tijolo | B8: Conservador | C8: Tijolo | D8: 0.1
A9: =$B9&"-"&$C9 -> Conservador-Híbridos | B9: Conservador | C9: Híbridos | D9: 0.1
A10: =$B10&"-"&$C10 -> Conservador-FOFs | B10: Conservador | C10: FOFs | D10: 0
A11: =$B11&"-"&$C11 -> Conservador-Desenvolvimento | B11: Conservador | C11: Desenvolvimento | D11: 0
A12: =$B12&"-"&$C12 -> Conservador-Hotelarias | B12: Conservador | C12: Hotelarias | D12: 0.3
... A18: =$B18&"-"&$C18 -> Moderado-Hotelarias | B18: Moderado | C18: Hotelarias | D18: 0.1
